insightconnect_plugin_runtime/__init__.py
insightconnect_plugin_runtime/action.py
insightconnect_plugin_runtime/cli.py
insightconnect_plugin_runtime/connection.py
insightconnect_plugin_runtime/dispatcher.py
insightconnect_plugin_runtime/exceptions.py
insightconnect_plugin_runtime/helper.py
insightconnect_plugin_runtime/metrics.py
insightconnect_plugin_runtime/plugin.py
insightconnect_plugin_runtime/schema.py
insightconnect_plugin_runtime/server.py
insightconnect_plugin_runtime/step.py
insightconnect_plugin_runtime/task.py
insightconnect_plugin_runtime/telemetry.py
insightconnect_plugin_runtime/trigger.py
insightconnect_plugin_runtime/util.py
insightconnect_plugin_runtime/variables.py
insightconnect_plugin_runtime/api/__init__.py
insightconnect_plugin_runtime/api/endpoints.py
insightconnect_plugin_runtime/api/schemas.py
insightconnect_plugin_runtime/clients/__init__.py
insightconnect_plugin_runtime/clients/aws_client.py
insightconnect_plugin_runtime/clients/oauth.py
insightconnect_plugin_runtime/data/input_message_schema.json
insightconnect_plugin_runtime/data/output_message_schema.json
tests/__init__.py
tests/plugin/__init__.py
tests/plugin/hello_world/__init__.py
tests/plugin/hello_world/hello_world/__init__.py
tests/plugin/hello_world/hello_world/setup.py
tests/plugin/hello_world/hello_world/komand_hello_world/__init__.py
tests/plugin/hello_world/hello_world/komand_hello_world/actions/__init__.py
tests/plugin/hello_world/hello_world/komand_hello_world/actions/hello/__init__.py
tests/plugin/hello_world/hello_world/komand_hello_world/actions/hello/action.py
tests/plugin/hello_world/hello_world/komand_hello_world/actions/hello/schema.py
tests/plugin/hello_world/hello_world/komand_hello_world/actions/return_bad_json/__init__.py
tests/plugin/hello_world/hello_world/komand_hello_world/actions/return_bad_json/action.py
tests/plugin/hello_world/hello_world/komand_hello_world/actions/return_bad_json/schema.py
insightconnect_plugin_runtime-6.4.2.dist-info/METADATA
insightconnect_plugin_runtime-6.4.2.dist-info/WHEEL
insightconnect_plugin_runtime-6.4.2.dist-info/top_level.txt
insightconnect_plugin_runtime-6.4.2.dist-info/RECORD
