Metadata-Version: 2.4
Name: insightconnect-plugin-runtime
Version: 6.4.2
Summary: InsightConnect Plugin Runtime
Home-page: https://github.com/rapid7/komand-plugin-sdk-python
Author: Rapid7 Integrations Alliance
Author-email: integrationalliance@rapid7.com
Classifier: Programming Language :: Python :: 3
Classifier: Operating System :: OS Independent
Classifier: Intended Audience :: Developers
Classifier: License :: OSI Approved :: MIT License
Classifier: Natural Language :: English
Classifier: Topic :: Software Development :: Build Tools
Requires-Dist: requests==2.32.5
Requires-Dist: python_jsonschema_objects==0.5.2
Requires-Dist: jsonschema==4.22.0
Requires-Dist: certifi==2026.1.4
Requires-Dist: Flask==3.1.2
Requires-Dist: gunicorn==23.0.0
Requires-Dist: greenlet==3.3.0
Requires-Dist: gevent==25.5.1
Requires-Dist: marshmallow==3.26.2
Requires-Dist: apispec==6.5.0
Requires-Dist: apispec-webframeworks==1.0.0
Requires-Dist: blinker==1.9.0
Requires-Dist: structlog==25.5.0
Requires-Dist: python-json-logger==2.0.7
Requires-Dist: Jinja2==3.1.6
Requires-Dist: python-dateutil==2.9.0.post0
Requires-Dist: opentelemetry-sdk==1.39.1
Requires-Dist: opentelemetry-instrumentation-flask==0.60b1
Requires-Dist: opentelemetry-exporter-otlp-proto-http==1.39.1
Requires-Dist: opentelemetry-instrumentation-requests==0.60b1
Requires-Dist: urllib3==2.6.3
Dynamic: author
Dynamic: author-email
Dynamic: classifier
Dynamic: description
Dynamic: description-content-type
Dynamic: home-page
Dynamic: requires-dist
Dynamic: summary
